east/__init__.py
east/log.py
east/main.py
mxos_east-0.0.5.dist-info/LICENSE
mxos_east-0.0.5.dist-info/METADATA
mxos_east-0.0.5.dist-info/WHEEL
mxos_east-0.0.5.dist-info/entry_points.txt
mxos_east-0.0.5.dist-info/top_level.txt
mxos_east-0.0.5.dist-info/RECORD
