Metadata-Version: 2.1
Name: mxos-east
Version: 0.0.5
Summary: Tool for build MXOS application.
Home-page: https://github.com/smartsnow/east
Author: Snow Yang
Author-email: snowyang.iot@outlook.com
License: UNKNOWN
Project-URL: Bug Tracker, https://github.com/smartsnow/east/issues
Platform: UNKNOWN
Classifier: Programming Language :: Python :: 3
Classifier: License :: OSI Approved :: MIT License
Classifier: Operating System :: OS Independent
Requires-Python: >=3.6
License-File: LICENSE
Requires-Dist: rich
